pkmap/PKM.py
pkmap/__init__.py
pkmap/appliance_data.py
pkmap/house_preview.py
pkmap/pkmap_data.py
pkmap/utils.py
pkmap-0.2.1.dist-info/LICENSE
pkmap-0.2.1.dist-info/METADATA
pkmap-0.2.1.dist-info/WHEEL
pkmap-0.2.1.dist-info/top_level.txt
pkmap-0.2.1.dist-info/RECORD
