Metadata-Version: 2.1
Name: pkmap
Version: 0.2.1
Summary: a dataset visualization generator supposed to                exhibit the imbalance for human eye acquisition
Home-page: https://github.com/pkmap/pkmap
Author: ZJ Lewous
Author-email: zj.lewous@gmail.com
License: Mozilla
Download-URL: https://github.com/pkmap/pkmap/tarball/master
Platform: UNKNOWN
Requires-Dist: numpy
Requires-Dist: pandas
Requires-Dist: matplotlib (==3.1.3)
Requires-Dist: seaborn
Requires-Dist: scikit-learn (>=0.21.2)
Requires-Dist: jupyter
Requires-Dist: tqdm
Provides-Extra: optional
Requires-Dist: nilmtk ; extra == 'optional'
